dict2graph/__init__.py
dict2graph/dict2graph.py
dict2graph/graph_object_transformer_meta_data.py
dict2graph/matcher_transformators_container.py
dict2graph/node.py
dict2graph/relation.py
dict2graph/transformers/__init__.py
dict2graph/transformers/_base.py
dict2graph/transformers/_types.py
dict2graph/transformers/generic_transformers.py
dict2graph/transformers/node_transformers.py
dict2graph/transformers/rel_transformers.py
dict2graph-3.2.1.dist-info/LICENSE.md
dict2graph-3.2.1.dist-info/METADATA
dict2graph-3.2.1.dist-info/WHEEL
dict2graph-3.2.1.dist-info/top_level.txt
dict2graph-3.2.1.dist-info/RECORD
