Metadata-Version: 2.1
Name: dict2graph
Version: 3.2.1
Summary: Class to extract, transform and load (ETL) dicts/json to a Neo4j graph
Home-page: https://git.connect.dzd-ev.de/dzdpythonmodules/dict2graph
Author: TB
Author-email: tim.bleimehl@helmholtz-muenchen.de
License: MIT
Requires-Python: >=3.9
License-File: LICENSE.md
Requires-Dist: py2neo
Requires-Dist: neo4j
Requires-Dist: graphio
Provides-Extra: docs
Requires-Dist: mkdocs ; extra == 'docs'
Requires-Dist: mkdocstrings[python] ; extra == 'docs'
Requires-Dist: mkdocs-autorefs ; extra == 'docs'
Requires-Dist: mkdocs-material ; extra == 'docs'
Provides-Extra: tests
Requires-Dist: pytest ; extra == 'tests'
Requires-Dist: deepdiff ; extra == 'tests'
